cwc/__init__.py
cwc/_cwc.py
cwc-0.1.2.dist-info/LICENSE
cwc-0.1.2.dist-info/METADATA
cwc-0.1.2.dist-info/WHEEL
cwc-0.1.2.dist-info/entry_points.txt
cwc-0.1.2.dist-info/top_level.txt
cwc-0.1.2.dist-info/RECORD
