Metadata-Version: 2.1
Name: cwc
Version: 0.1.2
Summary: cwc description
Home-page: https://github.com/kirin123kirin/cwc
Author: kirin123kirin
Author-email: kirin123kirin@gmail.com
License: MIT
Keywords: wordcloud
Platform: UNKNOWN
Classifier: Programming Language :: Python :: 3
Classifier: Programming Language :: Python :: 3.7
Classifier: Programming Language :: Python :: 3.8
Classifier: Programming Language :: Python :: 3.9
Classifier: Programming Language :: Python :: 3.10
Classifier: Programming Language :: Python :: 3.11
Classifier: Programming Language :: Python :: 3.12
Classifier: License :: OSI Approved :: MIT License
License-File: LICENSE
Requires-Dist: setuptools >=42
Requires-Dist: wheel
Requires-Dist: mecab-python3
Requires-Dist: janome
Requires-Dist: wordcloud
Requires-Dist: pyperclip
Provides-Extra: test
Requires-Dist: pytest ; extra == 'test'
Requires-Dist: pytest-cov ; extra == 'test'
Requires-Dist: psutil ; extra == 'test'
